README.md
setup.py
pyhydrogen/__init__.py
pyhydrogen.egg-info/PKG-INFO
pyhydrogen.egg-info/SOURCES.txt
pyhydrogen.egg-info/dependency_links.txt
pyhydrogen.egg-info/not-zip-safe
pyhydrogen.egg-info/top_level.txt