Metadata-Version: 1.0
Name: pyhydrogen
Version: 1.0.0
Summary: A python package that rick rolls users on setup and import!
Home-page: https://github.com/bulkypanda/pyhydrogen
Author: Arya Gummadi
Author-email: arya@gummadi.net
License: MIT License
Platform: UNKNOWN
